flot/__init__.py
flot/__main__.py
flot/buildapi.py
flot/common.py
flot/config.py
flot/sdist.py
flot/versionno.py
flot/wheel.py
flot-0.7.2.dist-info/entry_points.txt
flot-0.7.2.dist-info/WHEEL
flot-0.7.2.dist-info/METADATA
flot-0.7.2.dist-info/LICENSE
flot-0.7.2.dist-info/RECORD
