Metadata-Version: 2.1
Name: flot
Version: 0.7.2
Summary: Flot is a simple tool to easily build multiple packages (wheel and sdist) from a single repo without having to create a subdir or another repo for each package, and by simply listing which files to include.
Author-email: Philippe Ombredanne <pombredanne@nexb.com>, Thomas Kluyver <thomas@kluyver.me.uk>
Maintainer-email: Philippe Ombredanne <pombredanne@nexb.com>
Requires-Python: >=3.8
Classifier: Intended Audience :: Developers
Classifier: Programming Language :: Python :: 3
Classifier: Topic :: Software Development :: Libraries :: Python Modules
Requires-Dist: tomli; python_version < '3.11'
Requires-Dist: sphinx ; extra == "doc"
Requires-Dist: sphinxcontrib_github_alt ; extra == "doc"
Requires-Dist: sphinx-rtd-theme ; extra == "doc"
Requires-Dist: testpath ; extra == "test"
Requires-Dist: responses ; extra == "test"
Requires-Dist: pytest>=2.7.3 ; extra == "test"
Requires-Dist: pytest-cov ; extra == "test"
Requires-Dist: tomli ; extra == "test"
Requires-Dist: flake8 ; extra == "test"
Requires-Dist: doc8 ; extra == "test"
Requires-Dist: black ; extra == "test"
Requires-Dist: isort ; extra == "test"
Requires-Dist: bump-my-version ; extra == "test"
Requires-Dist: tox ; extra == "test"
Requires-Dist: twine ; extra == "test"
Project-URL: Source, https://github.com/nexB/flot
Provides-Extra: doc
Provides-Extra: test
